[
  {
    "id": "scene1",
    "title": "Scene 1 — Holmes entrance / exit",
    "page": 26,
    "file": "clips/IMG_2172_f6097-6554_silhouette.mp4",
    "poster": "clips/IMG_2172_f6097-6554_silhouette.jpg",
    "source": "IMG_2172.MOV (cut f6097–6554, 458 frames)",
    "notes": "Holmes faces front, turns to profile, then walks frame-right and exits. Plain single-subject silhouette.",
    "review": { "projectionist": "approved", "director": "pending" }
  },
  {
    "id": "scene2",
    "title": "Scene 2 — Moriarty menacing (I)",
    "page": "37-38",
    "file": "clips/scene2_moriarty.mp4",
    "poster": "clips/scene2_moriarty.jpg",
    "source": "IMG_2159.MOV (cut f914–1820, 907 frames)",
    "cue_in": "I pushed you…",
    "cue_out": "Beyond your control.",
    "notes": "Moriarty stands menacing at the table, then walks frame-left and exits. Plain single-subject silhouette.",
    "review": { "projectionist": "approved", "director": "pending" }
  },
  {
    "id": "scene3",
    "title": "Scene 3 — Moriarty menacing (II)",
    "page": "63-64",
    "file": "clips/IMG_2163_f1975-3414_silhouette.mp4",
    "poster": "clips/IMG_2163_f1975-3414_silhouette.jpg",
    "source": "IMG_2163.MOV (cut f1975–3414, 1441 frames)",
    "cue_in": "Moriarty",
    "cue_out": "I have work to do",
    "notes": "Moriarty enters frame-left, walks to centre, holds centre menacing/gesturing, then walks frame-right. Plain single-subject silhouette. Walk-in/out leg-gap timing de-popped so the legs separate on the same frame as the source instead of snapping open a couple frames late.",
    "review": { "projectionist": "approved", "director": "pending" }
  },
  {
    "id": "scene4",
    "title": "Scene 4 — Séance: Moriarty flickers to the Ghost",
    "page": 76,
    "file": "clips/scene4_seance_flicker_swap.mp4",
    "poster": "clips/scene4_seance_flicker_swap.jpg",
    "source": "IMG_2170.MOV",
    "notes": "Moriarty (man, coat, bowler) flickers out; the Ghost (woman, hooded cloak) flickers in. Flicker-swap effect straddles the transformation.",
    "review": { "projectionist": "approved", "director": "pending" }
  },
  {
    "id": "scene5",
    "title": "Scene 5 — The Falls: fight + falling deerstalker",
    "page": "97-98",
    "file": "clips/scene5_fight.mp4",
    "poster": "clips/scene5_fight.jpg",
    "source": "IMG_2167.MOV (whole file, 6834 frames, 114s)",
    "notes": "Moriarty solo, Holmes enters, the grapple at the falls, the deerstalker falls and lands, Holmes downed, Moriarty exits, Holmes returns alone. Single union silhouette.",
    "review": { "projectionist": "approved", "director": "pending" }
  },
  {
    "id": "scene6",
    "title": "Scene 6 — Moriarty reaches for Holmes",
    "page": 127,
    "file": "clips/scene6_moriarty.mp4",
    "poster": "clips/scene6_moriarty.jpg",
    "source": "IMG_2168.MOV (cut f2500–2750, 251 frames)",
    "cue_in": "I'll be back",
    "cue_out": "",
    "notes": "Moriarty stands center and reaches his right arm toward off-frame Holmes. Plain single-subject silhouette.",
    "review": { "projectionist": "approved", "director": "pending" }
  },
  {
    "section": "Additional Moriarty footage",
    "id": "additional-moriarty",
    "note": "Filmed before we did it with a scene read. Raw footage — not yet turned into shadows. Some are pretty good and we may want to use them, so they're posted here as source that can be processed into silhouettes if needed. All cut from IMG_2158.MOV."
  },
  {
    "id": "addl-clapping",
    "title": "Clapping",
    "raw": true,
    "file": "clips/clapping_IMG_2158_f8288-8794.mp4",
    "poster": "clips/clapping_IMG_2158_f8288-8794.jpg",
    "source": "IMG_2158.MOV (cut f8288–8794, 507 frames)",
    "notes": "Raw footage (color, no shadow processing yet)."
  },
  {
    "id": "addl-book",
    "title": "Book",
    "raw": true,
    "file": "clips/book_IMG_2158_f12096-12598.mp4",
    "poster": "clips/book_IMG_2158_f12096-12598.jpg",
    "source": "IMG_2158.MOV (cut f12096–12598, 503 frames)",
    "notes": "Raw footage (color, no shadow processing yet)."
  },
  {
    "id": "addl-hand-to-face",
    "title": "Hand to face",
    "raw": true,
    "file": "clips/hand_to_face_IMG_2158_f14980-15360.mp4",
    "poster": "clips/hand_to_face_IMG_2158_f14980-15360.jpg",
    "source": "IMG_2158.MOV (cut f14980–15360, 381 frames)",
    "notes": "Raw footage (color, no shadow processing yet)."
  },
  {
    "id": "addl-hand-to-face-take2",
    "title": "Hand to face (take 2)",
    "raw": true,
    "file": "clips/hand_to_face_take2_IMG_2158_f15723-16209.mp4",
    "poster": "clips/hand_to_face_take2_IMG_2158_f15723-16209.jpg",
    "source": "IMG_2158.MOV (cut f15723–16209, 487 frames)",
    "notes": "Raw footage (color, no shadow processing yet)."
  },
  {
    "id": "addl-arms-raised",
    "title": "Arms raised",
    "raw": true,
    "file": "clips/arms_raised_IMG_2158_f17570-17891.mp4",
    "poster": "clips/arms_raised_IMG_2158_f17570-17891.jpg",
    "source": "IMG_2158.MOV (cut f17570–17891, 322 frames)",
    "notes": "Raw footage (color, no shadow processing yet)."
  }
]
